{
  "atom": "inverse_schmitt_trigger_transform",
  "estimates": [
    {
      "mode": "empirical",
      "scalar_factor": 1.0,
      "confidence": 0.6,
      "n_trials": 7,
      "epsilon": 0.01,
      "input_regime": "hysteresis threshold crossings and in-band state retention around the default low and high thresholds",
      "notes": "Behavior is piecewise deterministic. Threshold perturbation checks show exact state retention away from the switching boundaries and bounded flips at the explicit low/high transition points."
    }
  ]
}
